autocurve/__init__.py
autocurve/fit.py
autocurve-0.0.1.dist-info/LICENSE
autocurve-0.0.1.dist-info/METADATA
autocurve-0.0.1.dist-info/WHEEL
autocurve-0.0.1.dist-info/top_level.txt
autocurve-0.0.1.dist-info/RECORD
