Metadata-Version: 2.1
Name: autocurve
Version: 0.0.1
Summary: Curve Fitting Tool
Home-page: https://github.com/leonarduschen/autocurve
Author: Leonardus Chen
Author-email: leonardus.chen@gmail.com
License: GPLv3+
Platform: UNKNOWN
Classifier: Programming Language :: Python :: 3
Classifier: License :: OSI Approved :: GNU General Public License v3 or later (GPLv3+)
Classifier: Operating System :: OS Independent
Requires-Dist: matplotlib (>=3.3.3)
Requires-Dist: numpy (==1.19.4)
Requires-Dist: imageio (==2.9.0)
